beets_copyartifacts3-0.1.6-py3.12-nspkg.pth
beets_copyartifacts3-0.1.6.dist-info/licenses/LICENSE
beetsplug/copyartifacts.py
beets_copyartifacts3-0.1.6.dist-info/METADATA
beets_copyartifacts3-0.1.6.dist-info/WHEEL
beets_copyartifacts3-0.1.6.dist-info/namespace_packages.txt
beets_copyartifacts3-0.1.6.dist-info/top_level.txt
beets_copyartifacts3-0.1.6.dist-info/RECORD
